mshap/__init__.py
mshap/mshap.py
mshap/test_mshap.py
mshap-0.2.2.dist-info/LICENSE
mshap-0.2.2.dist-info/METADATA
mshap-0.2.2.dist-info/WHEEL
mshap-0.2.2.dist-info/top_level.txt
mshap-0.2.2.dist-info/RECORD
