Metadata-Version: 2.1
Name: mshap
Version: 0.2.2
Summary: A Python port of R package mshap to interpret combined model outputs.
Author: Diadochokinetic
Author-email: diadochokinetic@googlemail.com
Requires-Python: >=3.10
License-File: LICENSE
Requires-Dist: pandas >=1.5.2
Requires-Dist: numpy >=1.23.5
